py3_brhk/__init__.py
py3_brhk/speaker.py
py3_brhk-1.1.10.dist-info/LICENSE
py3_brhk-1.1.10.dist-info/METADATA
py3_brhk-1.1.10.dist-info/WHEEL
py3_brhk-1.1.10.dist-info/top_level.txt
py3_brhk-1.1.10.dist-info/RECORD
